[
  {
    "id": "baoanduizhang",
    "name": "保安队长",
    "team": "townsfolk",
    "image": "https://www.funnynation.org/wp-content/uploads/2022/04/good.daf3b560-1.png",
    "edition": "ghs",
    "firstNight": 9,
    "firstNightReminder": "none",
    "otherNight": 0,
    "otherNightReminder": "none",
    "reminders": ["被保护"],
    "setup": false,
    "ability": "首夜，你可以选择顺时针的第几个玩家保护他，他将不会在夜间死亡。"
  },
  {
    "id": "kuaidiyuan",
    "name": "快递员",
    "image": "https://www.funnynation.org/wp-content/uploads/2022/04/good.daf3b560-1.png",
    "edition": "ghs",
    "team": "townsfolk",
    "firstNight": 10,
    "firstNightReminder": "none",
    "otherNight": 0,
    "otherNightReminder": "none",
    "reminders": ["收到暗号",
                  "醉酒"],
    "setup": false,
    "ability": "首夜，你可以给某一位玩家传递信息，告诉他一个接头暗号，如果他是好人阵营，他将收到暗号。如果他是邪恶阵营，你将从此处于醉酒状态。"
  },
  {
    "id": "banzhuanren",
    "name": "搬砖人",
    "image": "https://www.funnynation.org/wp-content/uploads/2022/04/good.daf3b560-1.png",
    "edition": "ghs",
    "team": "townsfolk",
    "firstNight": 8,
    "firstNightReminder": "none",
    "otherNight": 0,
    "otherNightReminder": "none",
    "reminders": [],
    "setup": false,
    "ability": "首夜，你会知道邪恶势力集中在你的哪一侧。（顺时针还是逆时针方向有更多的邪恶势力，相同的话也会得知。）"
  },
  {
    "id": "guanong",
    "name": "瓜农",
    "image": "https://www.funnynation.org/wp-content/uploads/2022/04/good.daf3b560-1.png",
    "edition": "ghs",
    "team": "townsfolk",
    "firstNight": 0,
    "firstNightReminder": "none",
    "otherNight": 4,
    "otherNightReminder": "none",
    "reminders": ["中毒"],
    "setup": false,
    "ability": "每夜（首夜除外），你可以给（除你以外的）玩家喷药，如果他是邪恶势力，他将中毒。不能连续两晚喷同一个人。"
  },
  {
    "id": "shenyi",
    "name": "神医",
    "image": "https://www.funnynation.org/wp-content/uploads/2022/04/good.daf3b560-1.png",
    "edition": "ghs",
    "team": "townsfolk",
    "firstNight": 0,
    "firstNightReminder": "none",
    "otherNight": 7,
    "otherNightReminder": "none",
    "reminders": [],
    "setup": false,
    "ability": "每夜（首夜除外），你可以得知任意两个存活玩家中，有几个人生病了（醉酒/中毒/疯狂）"
  },
  {
    "id": "jiubayingxiao",
    "name": "酒吧营销",
    "image": "https://www.funnynation.org/wp-content/uploads/2022/04/good.daf3b560-1.png",
    "edition": "ghs",
    "team": "townsfolk",
    "firstNight": 7,
    "firstNightReminder": "none",
    "otherNight": 8,
    "otherNightReminder": "none",
    "reminders": [],
    "setup": false,
    "ability": "每夜，你可以选择三名玩家，如果三个人都是同阵营玩家，你将因此疯狂一天一夜，之后处于醉酒状态且不再被唤醒。"
  },
  {
    "id": "shilaimu",
    "name": "史莱姆",
    "image": "https://www.funnynation.org/wp-content/uploads/2022/04/good.daf3b560-1.png",
    "edition": "ghs",
    "team": "townsfolk",
    "firstNight": 12,
    "firstNightReminder": "none",
    "otherNight": 9,
    "otherNightReminder": "none",
    "reminders": ["贴贴"],
    "setup": false,
    "ability": "每夜，你可以选择一名玩家，如果你死了，他也会死。（他死了你不会死）"
  },
  {
    "id": "meipo",
    "name": "媒婆",
    "image": "https://www.funnynation.org/wp-content/uploads/2022/04/good.daf3b560-1.png",
    "edition": "ghs",
    "team": "townsfolk",
    "firstNight": 0,
    "firstNightReminder": "none",
    "otherNight": 10,
    "otherNightReminder": "none",
    "reminders": ["好人情侣",
        "邪恶情侣",
        "带刀"],
    "setup": false,
    "ability": "每夜（除了首夜），你可以选择两位玩家喜结连理，如果他们是不同阵营玩家，你们将组成第三方阵营，之后你将不再被唤醒。"
  },
  {
    "id": "xingganheguan",
    "name": "性感荷官",
    "image": "https://www.funnynation.org/wp-content/uploads/2022/04/good.daf3b560-1.png",
    "edition": "ghs",
    "team": "townsfolk",
    "firstNight": 0,
    "firstNightReminder": "none",
    "otherNight": 14,
    "otherNightReminder": "none",
    "reminders": [],
    "setup": false,
    "ability": "每局一次，如果你被标记为即将处决，无论你最终是否被处决，你可以选择1名玩家，当晚你将得知他相邻两边的玩家有没有邪恶势力。"
  },
  {
    "id": "mianbaoshi",
    "name": "面包师",
    "image": "https://www.funnynation.org/wp-content/uploads/2022/04/good.daf3b560-1.png",
    "edition": "ghs",
    "team": "townsfolk",
    "firstNight": 0,
    "firstNightReminder": "none",
    "otherNight": 0,
    "otherNightReminder": "none",
    "reminders": ["健康"],
    "setup": false,
    "ability": "每局一次，在公聊阶段，你可以制作一个面包给别人，他将保持清醒状态直到第二天黄昏。"
  },
  {
    "id": "jichengren",
    "name": "继承人",
    "image": "https://www.funnynation.org/wp-content/uploads/2022/04/good.daf3b560-1.png",
    "edition": "ghs",
    "team": "townsfolk",
    "firstNight": 11,
    "firstNightReminder": "none",
    "otherNight": 3,
    "otherNightReminder": "none",
    "reminders": ["爹",
                  "醉酒"],
    "setup": false,
    "ability": "在游戏开局，你将选择一位玩家作为“爹”，在他死后你将继承他的技能。在此之前你将始终处于醉酒状态。（阵营不变）"
  },
  {
    "id": "woniubaobao",
    "name": "蜗牛宝宝",
    "image": "https://www.funnynation.org/wp-content/uploads/2022/04/good.daf3b560-1.png",
    "edition": "ghs",
    "team": "townsfolk",
    "firstNight": 0,
    "firstNightReminder": "none",
    "otherNight": 0,
    "otherNightReminder": "none",
    "reminders": ["+1生命",
                 "+2生命"],
    "setup": false,
    "ability": "如果你相邻身边的玩家死亡，你将多一条命。（最多+2）"
  },
  {
    "id": "yanshuojia",
    "name": "演说家",
    "image": "https://www.funnynation.org/wp-content/uploads/2022/04/good.daf3b560-1.png",
    "edition": "ghs",
    "team": "townsfolk",
    "firstNight": 0,
    "firstNightReminder": "none",
    "otherNight": 0,
    "otherNightReminder": "none",
    "reminders": ["演讲结束"],
    "setup": false,
    "ability": "每局一次，当你被标记为将被处决且没有其他提名时，你可以做一个1分钟左右的演讲，如果感动到说书人，你将不会被处决。"
  },
  {
    "id": "jiajiao",
    "name": "家教",
    "image": "https://www.funnynation.org/wp-content/uploads/2022/04/outsider.2c6bc66e.png",
    "edition": "ghs",
    "team": "outsider",
    "firstNight": 13,
    "firstNightReminder": "none",
    "otherNight": 0,
    "otherNightReminder": "none",
    "reminders": ["学生"],
    "setup": false,
    "ability": "开局首夜选择一位玩家当他的老师，他死后你需要痛苦忏悔半分钟，否则可能会死亡或一直处于醉酒/中毒状态。"
  },
  {
    "id": "paimaishi",
    "name": "拍卖师",
    "image": "https://www.funnynation.org/wp-content/uploads/2022/04/outsider.2c6bc66e.png",
    "edition": "ghs",
    "team": "outsider",
    "firstNight": 14,
    "firstNightReminder": "none",
    "otherNight": 0,
    "otherNightReminder": "none",
    "reminders": ["竞拍成功"],
    "setup": false,
    "ability": "开局首夜，在说书人提供的三件物品中（一次性信息或技能等）选择一件，在之后任意一天，以拍卖的形式，公开将他给与一位玩家。"
  },
  {
    "id": "fangchanzhongjie",
    "name": "房产中介",
    "image": "https://www.funnynation.org/wp-content/uploads/2022/04/outsider.2c6bc66e.png",
    "edition": "ghs",
    "team": "outsider",
    "firstNight": 15,
    "firstNightReminder": "none",
    "otherNight": 16,
    "otherNightReminder": "none",
    "reminders": ["客户"],
    "setup": false,
    "ability": "开局首夜，随机一位玩家成为你的客户，如果他发生了任何变化，你会在第二天夜里收到提示。"
  },
  {
    "id": "yongren",
    "name": "佣人",
    "image": "https://www.funnynation.org/wp-content/uploads/2022/04/outsider.2c6bc66e.png",
    "edition": "ghs",
    "team": "outsider",
    "firstNight": 0,
    "firstNightReminder": "none",
    "otherNight": 15,
    "otherNightReminder": "none",
    "reminders": ["指认成功",
        "指认失败"],
    "setup": false,
    "ability": "当你在夜里死的时候，你会被唤醒并指认一个凶手，如果是他杀了你，你将不会死。"
  },
  {
    "id": "yueyuzhe",
    "name": "越狱者",
    "image": "https://www.funnynation.org/wp-content/uploads/2022/04/minion.e02a5c96.png",
    "edition": "ghs",
    "team": "minion",
    "firstNight": 0,
    "firstNightReminder": "none",
    "otherNight": 2,
    "otherNightReminder": "none",
    "reminders": ["越狱了",
        "完成击杀"],
    "setup": true,
    "ability": "每夜你可以选择是否越狱，越狱之前你不会以任何方式死亡，但是不能投票。越狱后任意一天，你可以选择一名玩家，他将死亡。你会在之后一天夜里死亡。"
  },
  {
    "id": "cuimianshi",
    "name": "催眠师",
    "image": "https://www.funnynation.org/wp-content/uploads/2022/04/minion.e02a5c96.png",
    "edition": "ghs",
    "team": "minion",
    "firstNight": 4,
    "firstNightReminder": "none",
    "otherNight": 0,
    "otherNightReminder": "none",
    "reminders": ["变好人",
                 "变坏人"],
    "setup": false,
    "ability": "首夜，你可以将一位好人玩家转变为邪恶势力，他将保留他的技能，并得知邪恶势力的成员。[外来人口-1或+1]"
  },
  {
    "id": "shitouren",
    "name": "石头人",
    "image": "https://www.funnynation.org/wp-content/uploads/2022/04/minion.e02a5c96.png",
    "edition": "ghs",
    "team": "minion",
    "firstNight": 6,
    "firstNightReminder": "none",
    "otherNight": 13,
    "otherNightReminder": "none",
    "reminders": ["禁言"],
    "setup": false,
    "ability": "每夜，你可以选择任意一位存活玩家，他将不能在第二天公聊的阶段说话，直到黄昏（提名结束）。"
  },
  {
    "id": "kulougui",
    "name": "骷髅鬼",
    "image": "https://www.funnynation.org/wp-content/uploads/2022/04/minion.e02a5c96.png",
    "edition": "ghs",
    "team": "minion",
    "firstNight": 5,
    "firstNightReminder": "none",
    "otherNight": 0,
    "otherNightReminder": "none",
    "reminders": ["替死消耗"],
    "setup": false,
    "ability": "首夜，你可以在场上任意位置添加一个傀儡（虚拟玩家），你可以决定它的身份，但是它没有技能，也不能投票。当邪恶阵营的某位玩家第一次死的时候，傀儡会替死。"
  },
  {
    "id": "diyulong",
    "name": "地狱龙",
    "image": "https://www.funnynation.org/wp-content/uploads/2022/04/evil.8723a4ee-1.png",
    "edition": "ghs",
    "team": "demon",
    "firstNight": 0,
    "firstNightReminder": "none",
    "otherNight": 11,
    "otherNightReminder": "none",
    "reminders": ["地狱龙的选择",
        "非健康状态"],
    "setup": false,
    "ability": "每晚（首夜除外），选择一个玩家，他将死亡。他两边相邻的好人玩家如果今晚不是健康状态（中毒/醉酒/疯狂），也将死亡。"
  },
  {
    "id": "jimowangling",
    "name": "寂寞亡灵",
    "image": "https://www.funnynation.org/wp-content/uploads/2022/04/evil.8723a4ee-1.png",
    "edition": "ghs",
    "team": "demon",
    "firstNight": 0,
    "firstNightReminder": "none",
    "otherNight": 12,
    "otherNightReminder": "none",
    "reminders": ["中毒",
        "寂寞亡灵的选择"],
    "setup": false,
    "ability": "每晚（首夜除外），你可以选择一名玩家，他将死亡，与他有关系的随机一人可能也会死亡。"
  },
  {
    "id": "paikexi",
    "name": "派克西",
    "image": "https://www.funnynation.org/wp-content/uploads/2022/04/evil.8723a4ee-1.png",
    "edition": "ghs",
    "team": "demon",
    "firstNight": 0,
    "firstNightReminder": "none",
    "otherNight": 6,
    "otherNightReminder": "none",
    "reminders": ["暗杀成功",
        "暗杀失败"],
    "setup": false,
    "ability": "晚（首夜除外），你可以选择一位玩家，并指定他何时死亡。如果你暗杀失败（下次选人之前没杀成，被处决不算）随机一位好人玩家从此中毒。"
  },
  {
    "id": "chuoqi",
    "name": "啜泣",
    "image": "https://www.funnynation.org/wp-content/uploads/2022/04/evil.8723a4ee-1.png",
    "edition": "ghs",
    "team": "demon",
    "firstNight": 0,
    "firstNightReminder": "none",
    "otherNight": 5,
    "otherNightReminder": "none",
    "reminders": ["中毒",
        "死亡"],
    "setup": false,
    "ability": "每晚（首夜除外），你可以选择两位玩家，其中第一个人会中毒，另一位会死亡。"
  },
  {
    "id": "teyaojiabin",
    "name": "特邀嘉宾",
    "image": "https://www.funnynation.org/wp-content/uploads/2022/04/custom.402e9bc3.png",
    "edition": "ghs",
    "team": "traveler",
    "firstNight": 0,
    "firstNightReminder": "none",
    "otherNight": 0,
    "otherNightReminder": "none",
    "reminders": ["公聊+1"],
    "setup": false,
    "ability": "白天会因为你的到来延长一点。（处决后，公聊阶段+1）"
  },
  {
    "id": "meishijia",
    "name": "美食家",
    "image": "https://www.funnynation.org/wp-content/uploads/2022/04/custom.402e9bc3.png",
    "edition": "ghs",
    "team": "traveler",
    "firstNight": 0,
    "firstNightReminder": "none",
    "otherNight": 0,
    "otherNightReminder": "none",
    "reminders": [],
    "setup": false,
    "ability": "每天，如果没有人被处决死亡，你可以选择一个没有投票的玩家，他将死亡。"
  },
  {
    "id": "chuanzhang",
    "name": "船长",
    "image": "https://www.funnynation.org/wp-content/uploads/2022/04/custom.402e9bc3.png",
    "edition": "ghs",
    "team": "traveler",
    "firstNight": 0,
    "firstNightReminder": "none",
    "otherNight": 0,
    "otherNightReminder": "none",
    "reminders": [],
    "setup": false,
    "ability": "每天白天，你可以公开选择1对玩家，他们将强制互相提名。"
  },
  {
    "id": "fuduji",
    "name": "复读机",
    "image": "https://www.funnynation.org/wp-content/uploads/2022/04/custom.402e9bc3.png",
    "edition": "ghs",
    "team": "traveler",
    "firstNight": 0,
    "firstNightReminder": "none",
    "otherNight": 0,
    "otherNightReminder": "none",
    "reminders": [],
    "setup": false,
    "ability": "你可以通过经常重复某个人说话来逃避放逐。"
  },
  {
    "id": "miwujingling",
    "name": "迷雾精灵",
    "edition": "ghs",
    "image": "https://www.funnynation.org/wp-content/uploads/2022/04/custom.402e9bc3.png",
    "team": "traveler",
    "firstNight": 3,
    "firstNightReminder": "none",
    "otherNight": 1,
    "otherNightReminder": "none",
    "reminders": [],
    "setup": false,
    "ability": "每天夜间，你可以选择改变某个玩家的唤醒顺序。"
  }
]
